Workbook
Name Slicer_Sector: #N/A
Name Slicer_Ticker: #N/A

Sheet Portfolio
A1: Ticker | B1: Sector | C1: Purchase Price | D1: Current Price | E1: Quantitiy | F1: Investment | G1: Current value | H1: Profit/loss | I1: Return % | J1: Asset Allocation % | K1: contribution to profit/loss % | L1: Risk category
A2: AAPL | B2: Technology | C2: 150 | D2: =_xlfn.XLOOKUP(PortfolioTable[[#This Row],[Ticker]],'Market Data'!A2:A21,'Market Data'!B2:B21) -> 180 | E2: 10 | F2: =C2*E2 -> 1500 | G2: =D2*E2 -> 1800 | H2: =G2-F2 -> 300 | I2: =(G2-F2)/F2 -> 0.2 | J2: =PortfolioTable[[#This Row],[Current value]]/SUM(PortfolioTable[Current value]) -> 0.041903343 | K2: =PortfolioTable[[#This Row],[Profit/loss]]/$G$25 -> 0.056969237 | L2: =IF(PortfolioTable[[#This Row],[Return %]]>20%, "high performer", IF(PortfolioTable[[#This Row],[Return %]]>5%, "moderate performer", "underperformer")) -> moderate performer
A3: MSFT | B3: Technology | C3: 300 | D3: =_xlfn.XLOOKUP(PortfolioTable[[#This Row],[Ticker]],'Market Data'!A3:A22,'Market Data'!B3:B22) -> 350 | E3: 5 | F3: =C3*E3 -> 1500 | G3: =D3*E3 -> 1750 | H3: =G3-F3 -> 250 | I3: =(G3-F3)/F3 -> 0.16666667 | J3: =PortfolioTable[[#This Row],[Current value]]/SUM(PortfolioTable[Current value]) -> 0.040739361 | K3: =PortfolioTable[[#This Row],[Profit/loss]]/$G$25 -> 0.047474364 | L3: =IF(PortfolioTable[[#This Row],[Return %]]>20%, "high performer", IF(PortfolioTable[[#This Row],[Return %]]>5%, "moderate performer", "underperformer")) -> moderate performer
A4: TSLA | B4: Automative | C4: 220 | D4: =_xlfn.XLOOKUP(PortfolioTable[[#This Row],[Ticker]],'Market Data'!A4:A23,'Market Data'!B4:B23) -> 260 | E4: 8 | F4: =C4*E4 -> 1760 | G4: =D4*E4 -> 2080 | H4: =G4-F4 -> 320 | I4: =(G4-F4)/F4 -> 0.18181818 | J4: =PortfolioTable[[#This Row],[Current value]]/SUM(PortfolioTable[Current value]) -> 0.048421641 | K4: =PortfolioTable[[#This Row],[Profit/loss]]/$G$25 -> 0.060767186 | L4: =IF(PortfolioTable[[#This Row],[Return %]]>20%, "high performer", IF(PortfolioTable[[#This Row],[Return %]]>5%, "moderate performer", "underperformer")) -> moderate performer
A5: NVDA | B5: Technology | C5: 500 | D5: =_xlfn.XLOOKUP(PortfolioTable[[#This Row],[Ticker]],'Market Data'!A5:A24,'Market Data'!B5:B24) -> 650 | E5: 4 | F5: =C5*E5 -> 2000 | G5: =D5*E5 -> 2600 | H5: =G5-F5 -> 600 | I5: =(G5-F5)/F5 -> 0.3 | J5: =PortfolioTable[[#This Row],[Current value]]/SUM(PortfolioTable[Current value]) -> 0.060527051 | K5: =PortfolioTable[[#This Row],[Profit/loss]]/$G$25 -> 0.11393847 | L5: =IF(PortfolioTable[[#This Row],[Return %]]>20%, "high performer", IF(PortfolioTable[[#This Row],[Return %]]>5%, "moderate performer", "underperformer")) -> high performer
A6: AMZN | B6: Consumer Discretionary | C6: 130 | D6: =_xlfn.XLOOKUP(PortfolioTable[[#This Row],[Ticker]],'Market Data'!A6:A25,'Market Data'!B6:B25) -> 160 | E6: 12 | F6: =C6*E6 -> 1560 | G6: =D6*E6 -> 1920 | H6: =G6-F6 -> 360 | I6: =(G6-F6)/F6 -> 0.23076923 | J6: =PortfolioTable[[#This Row],[Current value]]/SUM(PortfolioTable[Current value]) -> 0.044696899 | K6: =PortfolioTable[[#This Row],[Profit/loss]]/$G$25 -> 0.068363084 | L6: =IF(PortfolioTable[[#This Row],[Return %]]>20%, "high performer", IF(PortfolioTable[[#This Row],[Return %]]>5%, "moderate performer", "underperformer")) -> high performer
A7: GOOGL | B7: Technology | C7: 120 | D7: =_xlfn.XLOOKUP(PortfolioTable[[#This Row],[Ticker]],'Market Data'!A7:A26,'Market Data'!B7:B26) -> 145 | E7: 15 | F7: =C7*E7 -> 1800 | G7: =D7*E7 -> 2175 | H7: =G7-F7 -> 375 | I7: =(G7-F7)/F7 -> 0.20833333 | J7: =PortfolioTable[[#This Row],[Current value]]/SUM(PortfolioTable[Current value]) -> 0.050633206 | K7: =PortfolioTable[[#This Row],[Profit/loss]]/$G$25 -> 0.071211546 | L7: =IF(PortfolioTable[[#This Row],[Return %]]>20%, "high performer", IF(PortfolioTable[[#This Row],[Return %]]>5%, "moderate performer", "underperformer")) -> high performer
A8: META | B8: Technology | C8: 280 | D8: =_xlfn.XLOOKUP(PortfolioTable[[#This Row],[Ticker]],'Market Data'!A8:A27,'Market Data'!B8:B27) -> 340 | E8: 7 | F8: =C8*E8 -> 1960 | G8: =D8*E8 -> 2380 | H8: =G8-F8 -> 420 | I8: =(G8-F8)/F8 -> 0.21428571 | J8: =PortfolioTable[[#This Row],[Current value]]/SUM(PortfolioTable[Current value]) -> 0.055405531 | K8: =PortfolioTable[[#This Row],[Profit/loss]]/$G$25 -> 0.079756931 | L8: =IF(PortfolioTable[[#This Row],[Return %]]>20%, "high performer", IF(PortfolioTable[[#This Row],[Return %]]>5%, "moderate performer", "underperformer")) -> high performer
A9: JPM | B9: Financials | C9: 140 | D9: =_xlfn.XLOOKUP(PortfolioTable[[#This Row],[Ticker]],'Market Data'!A9:A28,'Market Data'!B9:B28) -> 165 | E9: 20 | F9: =C9*E9 -> 2800 | G9: =D9*E9 -> 3300 | H9: =G9-F9 -> 500 | I9: =(G9-F9)/F9 -> 0.17857143 | J9: =PortfolioTable[[#This Row],[Current value]]/SUM(PortfolioTable[Current value]) -> 0.076822795 | K9: =PortfolioTable[[#This Row],[Profit/loss]]/$G$25 -> 0.094948728 | L9: =IF(PortfolioTable[[#This Row],[Return %]]>20%, "high performer", IF(PortfolioTable[[#This Row],[Return %]]>5%, "moderate performer", "underperformer")) -> moderate performer
A10: BAC | B10: Financials | C10: 30 | D10: =_xlfn.XLOOKUP(PortfolioTable[[#This Row],[Ticker]],'Market Data'!A10:A29,'Market Data'!B10:B29) -> 35 | E10: 50 | F10: =C10*E10 -> 1500 | G10: =D10*E10 -> 1750 | H10: =G10-F10 -> 250 | I10: =(G10-F10)/F10 -> 0.16666667 | J10: =PortfolioTable[[#This Row],[Current value]]/SUM(PortfolioTable[Current value]) -> 0.040739361 | K10: =PortfolioTable[[#This Row],[Profit/loss]]/$G$25 -> 0.047474364 | L10: =IF(PortfolioTable[[#This Row],[Return %]]>20%, "high performer", IF(PortfolioTable[[#This Row],[Return %]]>5%, "moderate performer", "underperformer")) -> moderate performer
A11: V | B11: Financials | C11: 220 | D11: =_xlfn.XLOOKUP(PortfolioTable[[#This Row],[Ticker]],'Market Data'!A11:A30,'Market Data'!B11:B30) -> 270 | E11: 10 | F11: =C11*E11 -> 2200 | G11: =D11*E11 -> 2700 | H11: =G11-F11 -> 500 | I11: =(G11-F11)/F11 -> 0.22727273 | J11: =PortfolioTable[[#This Row],[Current value]]/SUM(PortfolioTable[Current value]) -> 0.062855014 | K11: =PortfolioTable[[#This Row],[Profit/loss]]/$G$25 -> 0.094948728 | L11: =IF(PortfolioTable[[#This Row],[Return %]]>20%, "high performer", IF(PortfolioTable[[#This Row],[Return %]]>5%, "moderate performer", "underperformer")) -> high performer
A12: MA | B12: Financials | C12: 350 | D12: =_xlfn.XLOOKUP(PortfolioTable[[#This Row],[Ticker]],'Market Data'!A12:A31,'Market Data'!B12:B31) -> 420 | E12: 6 | F12: =C12*E12 -> 2100 | G12: =D12*E12 -> 2520 | H12: =G12-F12 -> 420 | I12: =(G12-F12)/F12 -> 0.2 | J12: =PortfolioTable[[#This Row],[Current value]]/SUM(PortfolioTable[Current value]) -> 0.05866468 | K12: =PortfolioTable[[#This Row],[Profit/loss]]/$G$25 -> 0.079756931 | L12: =IF(PortfolioTable[[#This Row],[Return %]]>20%, "high performer", IF(PortfolioTable[[#This Row],[Return %]]>5%, "moderate performer", "underperformer")) -> moderate performer
A13: NFLX | B13: Communication services | C13: 400 | D13: =_xlfn.XLOOKUP(PortfolioTable[[#This Row],[Ticker]],'Market Data'!A13:A32,'Market Data'!B13:B32) -> 480 | E13: 5 | F13: =C13*E13 -> 2000 | G13: =D13*E13 -> 2400 | H13: =G13-F13 -> 400 | I13: =(G13-F13)/F13 -> 0.2 | J13: =PortfolioTable[[#This Row],[Current value]]/SUM(PortfolioTable[Current value]) -> 0.055871124 | K13: =PortfolioTable[[#This Row],[Profit/loss]]/$G$25 -> 0.075958982 | L13: =IF(PortfolioTable[[#This Row],[Return %]]>20%, "high performer", IF(PortfolioTable[[#This Row],[Return %]]>5%, "moderate performer", "underperformer")) -> moderate performer
... A21: ADBE | B21: Technology | C21: 500 | D21: =_xlfn.XLOOKUP(PortfolioTable[[#This Row],[Ticker]],'Market Data'!A21:A40,'Market Data'!B21:B40) -> 580 | E21: 3 | F21: =C21*E21 -> 1500 | G21: =D21*E21 -> 1740 | H21: =G21-F21 -> 240 | I21: =(G21-F21)/F21 -> 0.16 | J21: =PortfolioTable[[#This Row],[Current value]]/SUM(PortfolioTable[Current value]) -> 0.040506565 | K21: =PortfolioTable[[#This Row],[Profit/loss]]/$G$25 -> 0.045575389 | L21: =IF(PortfolioTable[[#This Row],[Return %]]>20%, "high performer", IF(PortfolioTable[[#This Row],[Return %]]>5%, "moderate performer", "underperformer")) -> moderate performer
F23: Total Investment | G23: =SUM(F2:F21) -> 37690
F24: Total current value | G24: =SUM(G2:G21) -> 42956
F25: Total profit | G25: =SUM(H2:H21) -> 5266
F26: Total return % | G26: =(G24-G23)/G23 -> 0.13971876
F27: Best performer | G27: =MAX(I2:I21) -> 0.3
F28: Worst performer | G28: =MIN(I2:I21) -> -0.15555556
F29: Largest position | G29: =MAX(PortfolioTable[Current value]) -> 3300
F30: Largest position value | G30: =_xlfn.XLOOKUP(MAX(PortfolioTable[Current value]),PortfolioTable[Current value],PortfolioTable[Ticker]) -> JPM

Sheet Dashboard
A1: Investment Portfolio Dashboard
A2: Prepared by: Lamis Ben Abdessamad
A3: Date: 20/06/2026
A4: KPI | B4: Value
A5: Total Investment | B5: =Portfolio!G23 -> 37690
A6: Current value | B6: =Portfolio!G24 -> 42956
A7: Total Profit/Loss | B7: =Portfolio!G25 -> 5266
A8: Portfolio Return % | B8: =Portfolio!G26 -> 0.13971876
A9: Number of Holdings | B9: =COUNTA(PortfolioTable[Ticker]) -> 20
A10: Largest position value | B10: =Portfolio!G29 -> 3300
A11: Largest position | B11: =Portfolio!G30 -> JPM
A12: Largest position weight % | B12: =B10/B6 -> 0.076822795
A13: Best return | B13: =Portfolio!G27 -> 0.3
A14: Worst return | B14: =Portfolio!G28 -> -0.15555556
A15: Portfolio status | B15: =IF(B8>0,"Profitable","Loss") -> Profitable
A16: Winning positions | B16: =COUNTIF(PortfolioTable[Return %],">0") -> 17
A17: Losing positions | B17: =COUNTIF(PortfolioTable[Return %],"<0") -> 3
A18: Number of sectors | B18: =COUNTA(_xlfn.UNIQUE(PortfolioTable[Sector])) -> 8
A19: Largest sector | B19: Technology
A20: Largest sector weight % | B20: 0.32
A21: Best Performer | B21: =_xlfn.XLOOKUP(MAX(PortfolioTable[Return %]),PortfolioTable[Return %],PortfolioTable[Ticker]) -> NVDA
A22: Worst Performer | B22: =_xlfn.XLOOKUP(MIN(PortfolioTable[Return %]),PortfolioTable[Return %],PortfolioTable[Ticker]) -> INTC

Sheet Sector analysis
A3: Sector | B3: Allocation %
A4: Automative | B4: 0.048421641
A5: Communication services | B5: 0.10010243
A6: Consumer Discretionary | B6: 0.044696899
A7: Consumer staples | B7: 0.10510755
A8: Energy | B8: 0.10731912
A9: Financial Technology | B9: 0.030170407
A10: Financials | B10: 0.23908185
A11: Technology | B11: 0.3251001
A12: Grand Total | B12: 1

Sheet Market Data
A1: Ticker | B1: Current Price
A2: AAPL | B2: 180
A3: MSFT | B3: 350
A4: TSLA | B4: 260
A5: NVDA | B5: 650
A6: AMZN | B6: 160
A7: GOOGL | B7: 145
A8: META | B8: 340
A9: JPM | B9: 165
A10: BAC | B10: 35
A11: V | B11: 270
A12: MA | B12: 420
A13: NFLX | B13: 480
... A21: ADBE | B21: 580

Sheet Summary
